checkers_main/__init__.py
checkers_main/game.py
checkers_main/utility.py
checkers_main/static/images/checkers.png
checkers_imp_adv_coding_proj-0.2.2.dist-info/METADATA
checkers_imp_adv_coding_proj-0.2.2.dist-info/WHEEL
checkers_imp_adv_coding_proj-0.2.2.dist-info/entry_points.txt
checkers_imp_adv_coding_proj-0.2.2.dist-info/top_level.txt
checkers_imp_adv_coding_proj-0.2.2.dist-info/RECORD
