Metadata-Version: 2.1
Name: checkers-imp-adv-coding-proj
Version: 0.2.2
Summary: Checkers implementation in python based on the international draughts
Author: Christian DY
Author-email: techscreed@gmail.com
Requires-Dist: pillow
Requires-Dist: pygame
Requires-Dist: setuptools
